yandex/__init__.py
yandex/cloud/__init__.py
yandex/cloud/validation_pb2.py
yandex/cloud/validation_pb2_grpc.py
yandex/cloud/access/__init__.py
yandex/cloud/access/access_pb2.py
yandex/cloud/access/access_pb2_grpc.py
yandex/cloud/ai/__init__.py
yandex/cloud/ai/foundation_models/__init__.py
yandex/cloud/ai/foundation_models/v1/__init__.py
yandex/cloud/ai/foundation_models/v1/text_common_pb2.py
yandex/cloud/ai/foundation_models/v1/text_common_pb2_grpc.py
yandex/cloud/ai/foundation_models/v1/embedding/__init__.py
yandex/cloud/ai/foundation_models/v1/embedding/embedding_service_pb2.py
yandex/cloud/ai/foundation_models/v1/embedding/embedding_service_pb2_grpc.py
yandex/cloud/ai/foundation_models/v1/image_generation/__init__.py
yandex/cloud/ai/foundation_models/v1/image_generation/image_generation_pb2.py
yandex/cloud/ai/foundation_models/v1/image_generation/image_generation_pb2_grpc.py
yandex/cloud/ai/foundation_models/v1/image_generation/image_generation_service_pb2.py
yandex/cloud/ai/foundation_models/v1/image_generation/image_generation_service_pb2_grpc.py
yandex/cloud/ai/foundation_models/v1/text_classification/__init__.py
yandex/cloud/ai/foundation_models/v1/text_classification/text_classification_pb2.py
yandex/cloud/ai/foundation_models/v1/text_classification/text_classification_pb2_grpc.py
yandex/cloud/ai/foundation_models/v1/text_classification/text_classification_service_pb2.py
yandex/cloud/ai/foundation_models/v1/text_classification/text_classification_service_pb2_grpc.py
yandex/cloud/ai/foundation_models/v1/text_generation/__init__.py
yandex/cloud/ai/foundation_models/v1/text_generation/text_generation_service_pb2.py
yandex/cloud/ai/foundation_models/v1/text_generation/text_generation_service_pb2_grpc.py
yandex/cloud/ai/llm/__init__.py
yandex/cloud/ai/llm/v1alpha/__init__.py
yandex/cloud/ai/llm/v1alpha/llm_pb2.py
yandex/cloud/ai/llm/v1alpha/llm_pb2_grpc.py
yandex/cloud/ai/llm/v1alpha/llm_service_pb2.py
yandex/cloud/ai/llm/v1alpha/llm_service_pb2_grpc.py
yandexcloud-0.288.0.dist-info/AUTHORS
yandexcloud-0.288.0.dist-info/LICENSE
yandexcloud-0.288.0.dist-info/METADATA
yandexcloud-0.288.0.dist-info/WHEEL
yandexcloud-0.288.0.dist-info/top_level.txt
yandexcloud-0.288.0.dist-info/RECORD
