Metadata-Version: 2.1
Name: yandexcloud
Version: 0.288.0
Summary: The Yandex.Cloud official SDK
Home-page: https://github.com/yandex-cloud/python-sdk
Author: Yandex LLC
Author-email: cloud@support.yandex.ru
License: MIT
Classifier: Programming Language :: Python
Classifier: Programming Language :: Python :: 3
Classifier: Programming Language :: Python :: 3.8
Classifier: Programming Language :: Python :: 3.9
Classifier: Programming Language :: Python :: 3.10
Classifier: Programming Language :: Python :: 3.11
Classifier: Programming Language :: Python :: 3.12
License-File: LICENSE
License-File: AUTHORS
Requires-Dist: cryptography >=2.8
Requires-Dist: grpcio >=1.59.3
Requires-Dist: protobuf >=4.23.4
Requires-Dist: googleapis-common-protos >=1.59.1
Requires-Dist: pyjwt >=1.7.1
Requires-Dist: requests >=2.22.0
Requires-Dist: six >=1.14.0
